pig/__init__.py
pig/api_client.py
pig/cli.py
pig/connection_session.py
pig/connections.py
pig/machines.py
pig/pig.py
pig/sync_wrapper.py
pig_python-0.1.2.dist-info/METADATA
pig_python-0.1.2.dist-info/WHEEL
pig_python-0.1.2.dist-info/entry_points.txt
pig_python-0.1.2.dist-info/licenses/LICENSE
pig_python-0.1.2.dist-info/RECORD
