Metadata-Version: 2.4
Name: pig-python
Version: 0.1.2
Summary: pig
Author-email: Erik Dunteman <erik@pig.dev>
License-File: LICENSE
Requires-Python: >=3.7
Requires-Dist: aiohttp-retry>=2.8.0
Requires-Dist: aiohttp>=3.8.0
Requires-Dist: click>=8.0.0
Requires-Dist: iso8601>=1.0.0
Requires-Dist: simple-term-menu>=1.0.0
Requires-Dist: tabulate>=0.9.0
Requires-Dist: typing-extensions
Provides-Extra: dev
Requires-Dist: build; extra == 'dev'
Requires-Dist: ruff>=0.3.0; extra == 'dev'
Requires-Dist: twine; extra == 'dev'
